owi_data_api_2_pandas/__init__.py
owi_data_api_2_pandas/io.py
owi_data_api_2_pandas/version.py
owi_data_api_2_pandas-0.1.0.dist-info/LICENSE.TXT
owi_data_api_2_pandas-0.1.0.dist-info/WHEEL
owi_data_api_2_pandas-0.1.0.dist-info/METADATA
owi_data_api_2_pandas-0.1.0.dist-info/RECORD
