Metadata-Version: 2.1
Name: owi-data-api-2-pandas
Version: 0.1.0
Summary: OWI data 2 pandas is a package developed to ease the interaction with the OWI measurement data API
Author: Yusuf Destan
Author-email: yusuf.destan@vub.be
Requires-Python: >=3.8,<4.0
Classifier: Programming Language :: Python :: 3
Classifier: Programming Language :: Python :: 3.10
Classifier: Programming Language :: Python :: 3.8
Classifier: Programming Language :: Python :: 3.9
Requires-Dist: pandas (>=1.3.4,<2.0.0)
Requires-Dist: python-dotenv (>=0.20.0,<0.21.0)
Requires-Dist: requests (>=2.27.1,<3.0.0)
